{
"type": "FeatureCollection",
"name": "country_ids",
"crs": { "type": "name", "properties": { "name": "urn:ogc:def:crs:OGC:1.3:CRS84" } },
"features": [
{ "type": "Feature", "properties": { "lat": 22.210928, "lon": 113.552971, "id": 1 }, "geometry": { "type": "Point", "coordinates": [ 113.552971, 22.210928 ] } },
{ "type": "Feature", "properties": { "lat": 51.509865, "lon": -0.118092, "id": 2 }, "geometry": { "type": "Point", "coordinates": [ -0.118092, 51.509865 ] } },
{ "type": "Feature", "properties": { "lat": 37.5326, "lon": 127.024612, "id": 3 }, "geometry": { "type": "Point", "coordinates": [ 127.024612, 37.5326 ] } },
{ "type": "Feature", "properties": { "lat": 36.0, "lon": 137.0, "id": 4 }, "geometry": { "type": "Point", "coordinates": [ 137.0, 36.0 ] } },
{ "type": "Feature", "properties": { "lat": 48.383022, "lon": 31.1828699, "id": 5 }, "geometry": { "type": "Point", "coordinates": [ 31.1828699, 48.383022 ] } },
{ "type": "Feature", "properties": { "lat": 56.923946, "lon": 24.1371, "id": 6 }, "geometry": { "type": "Point", "coordinates": [ 24.1371, 56.923946 ] } },
{ "type": "Feature", "properties": { "lat": 41.015137, "lon": 28.97953, "id": 7 }, "geometry": { "type": "Point", "coordinates": [ 28.97953, 41.015137 ] } },
{ "type": "Feature", "properties": { "lat": 44.439663, "lon": 26.096306, "id": 8 }, "geometry": { "type": "Point", "coordinates": [ 26.096306, 44.439663 ] } },
{ "type": "Feature", "properties": { "lat": 52.237049, "lon": 21.017532, "id": 9 }, "geometry": { "type": "Point", "coordinates": [ 21.017532, 52.237049 ] } },
{ "type": "Feature", "properties": { "lat": 28.6448, "lon": 77.216721, "id": 10 }, "geometry": { "type": "Point", "coordinates": [ 77.216721, 28.6448 ] } },
{ "type": "Feature", "properties": { "lat": 52.370216, "lon": 4.895168, "id": 11 }, "geometry": { "type": "Point", "coordinates": [ 4.895168, 52.370216 ] } },
{ "type": "Feature", "properties": { "lat": 21.033333, "lon": 105.849998, "id": 12 }, "geometry": { "type": "Point", "coordinates": [ 105.849998, 21.033333 ] } },
{ "type": "Feature", "properties": { "lat": 43.238949, "lon": 76.889709, "id": 13 }, "geometry": { "type": "Point", "coordinates": [ 76.889709, 43.238949 ] } },
{ "type": "Feature", "properties": { "lat": 52.520008, "lon": 13.404954, "id": 14 }, "geometry": { "type": "Point", "coordinates": [ 13.404954, 52.520008 ] } },
{ "type": "Feature", "properties": { "lat": 40.416775, "lon": -3.70379, "id": 15 }, "geometry": { "type": "Point", "coordinates": [ -3.70379, 40.416775 ] } },
{ "type": "Feature", "properties": { "lat": 48.864716, "lon": 2.349014, "id": 16 }, "geometry": { "type": "Point", "coordinates": [ 2.349014, 48.864716 ] } }
]
}
